nandg_distributions/Binomialdistribution.py
nandg_distributions/Gaussiandistribution.py
nandg_distributions/Generaldistribution.py
nandg_distributions/__init__.py
nandg_distributions-1.0.dist-info/DESCRIPTION.rst
nandg_distributions-1.0.dist-info/METADATA
nandg_distributions-1.0.dist-info/RECORD
nandg_distributions-1.0.dist-info/WHEEL
nandg_distributions-1.0.dist-info/metadata.json
nandg_distributions-1.0.dist-info/top_level.txt
