Metadata-Version: 2.0
Name: nandg-distributions
Version: 1.0
Summary: Gaussian & Binomial distributions
Home-page: UNKNOWN
Author: Shubham Trivedi
Author-email: trivedi700@gmail.com
License: UNKNOWN
Platform: UNKNOWN
